dr_wandb/__init__.py
dr_wandb/constants.py
dr_wandb/downloader.py
dr_wandb/fetch.py
dr_wandb/history_entry_record.py
dr_wandb/py.typed
dr_wandb/run_record.py
dr_wandb/store.py
dr_wandb/utils.py
dr_wandb/cli/__init__.py
dr_wandb/cli/download.py
dr_wandb/cli/postgres_download.py
dr_wandb-0.1.2.dist-info/METADATA
dr_wandb-0.1.2.dist-info/WHEEL
dr_wandb-0.1.2.dist-info/entry_points.txt
dr_wandb-0.1.2.dist-info/licenses/LICENSE
dr_wandb-0.1.2.dist-info/RECORD
