Metadata-Version: 2.4
Name: dr-wandb
Version: 0.1.2
Summary: Interact with wandb from python
Author-email: Danielle Rothermel <danielle.rothermel@gmail.com>
License-File: LICENSE
Requires-Python: >=3.12
Requires-Dist: pandas>=2.3.2
Requires-Dist: pyarrow>=21.0.0
Requires-Dist: sqlalchemy>=2.0.43
Requires-Dist: typer>=0.20.0
Requires-Dist: wandb>=0.21.4
